Metadata-Version: 1.1
Name: m1keycalculator
Version: 0.0.1
Summary: A very basic calculator
Home-page: UNKNOWN
Author: Mithilesh Tiwari
Author-email: shubhamtiwari.tiwari84@gmail.com
License: MIT
Keywords: calculator
Platform: UNKNOWN
Classifier: Development Status :: 5 - Production/Stable
Classifier: Intended Audience :: Education
Classifier: License :: OSI Approved :: MIT License
Classifier: Programming Language :: Python :: 3
